LICENSE.txt
MANIFEST.in
README.rst
ez_setup.py
pyproject.toml
setup.cfg
setup.py
docs/Makefile
docs/make.bat
pybedtools/_Window.pyx
pybedtools/__init__.py
pybedtools/bedtool.py
pybedtools/cbedtools.cpp
pybedtools/cbedtools.pxd
pybedtools/cbedtools.pyx
pybedtools/featurefuncs.cpp
pybedtools/featurefuncs.pyx
pybedtools/filenames.py
pybedtools/genome_registry.py
pybedtools/helpers.py
pybedtools/logger.py
pybedtools/parallel.py
pybedtools/paths.py
pybedtools/settings.py
pybedtools/stats.py
pybedtools/version.py
pybedtools.egg-info/PKG-INFO
pybedtools.egg-info/SOURCES.txt
pybedtools.egg-info/dependency_links.txt
pybedtools.egg-info/not-zip-safe
pybedtools.egg-info/requires.txt
pybedtools.egg-info/top_level.txt
pybedtools/contrib/__init__.py
pybedtools/contrib/bigbed.py
pybedtools/contrib/bigwig.py
pybedtools/contrib/intersection_matrix.py
pybedtools/contrib/long_range_interaction.py
pybedtools/contrib/plotting.py
pybedtools/contrib/venn_maker.py
pybedtools/include/bedFile.cpp
pybedtools/include/bedFile.h
pybedtools/include/fileType.cpp
pybedtools/include/fileType.h
pybedtools/include/gzstream.cpp
pybedtools/include/gzstream.h
pybedtools/include/lineFileUtilities.h
pybedtools/test/__init__.py
pybedtools/test/gchart-expected.png
pybedtools/test/genomepy_integration.py
pybedtools/test/mpl-expected.png
pybedtools/test/prevent_open_file_regression
pybedtools/test/regression_tests.py
pybedtools/test/test_1.py
pybedtools/test/test_cases.yaml
pybedtools/test/test_cbedtools.py
pybedtools/test/test_contrib.py
pybedtools/test/test_gzip_support.py
pybedtools/test/test_helpers.py
pybedtools/test/test_issues.py
pybedtools/test/test_iter.py
pybedtools/test/test_len_leak.py
pybedtools/test/test_merge215.yaml
pybedtools/test/test_merge227.yaml
pybedtools/test/test_pathlib.py
pybedtools/test/test_shuffle215.yaml
pybedtools/test/test_shuffle227.yaml
pybedtools/test/tfuncs.py
pybedtools/test/data/1000genomes-example.vcf
pybedtools/test/data/164.gtf
pybedtools/test/data/BEAF_Kc_Bushey_2009.bed
pybedtools/test/data/BEAF_Mbn2_Bushey_2009.bed
pybedtools/test/data/CTCF_Kc_Bushey_2009.bed
pybedtools/test/data/CTCF_Mbn2_Bushey_2009.bed
pybedtools/test/data/Cp190_Kc_Bushey_2009.bed
