Metadata-Version: 2.2
Name: pybedtools
Version: 0.12.0
Summary: Wrapper around BEDTools for bioinformatics work
Home-page: https://github.com/daler/pybedtools
Download-URL: 
Maintainer: Ryan Dale
Maintainer-email: ryan.dale@nih.gov
License: MIT
Classifier: Development Status :: 5 - Production/Stable
Classifier: Intended Audience :: Science/Research
Classifier: License :: OSI Approved :: MIT License
Classifier: Topic :: Scientific/Engineering :: Bio-Informatics
Classifier: Programming Language :: Python
Classifier: Programming Language :: Python :: 3
Classifier: Programming Language :: Python :: 3.6
Classifier: Programming Language :: Python :: 3.7
Classifier: Programming Language :: Python :: 3.8
Classifier: Topic :: Software Development :: Libraries :: Python Modules
License-File: LICENSE.txt
Requires-Dist: numpy
Requires-Dist: pysam
Requires-Dist: pandas
Dynamic: classifier
Dynamic: description
Dynamic: home-page
Dynamic: license
Dynamic: maintainer
Dynamic: maintainer-email
